[
    {
        "id": "1",
        "name": "กางเกงในหมาสามขา",
        "picture": "images/icon-1.png",
        "price": 79
    },
    {
        "id": "2",
        "name": "กางเกงใน เย็นจัด ไม่รัดจริง",
        "picture": "images/icon-2.png",
        "price": 79
    },
    {
        "id": "3",
        "name": "กางเกงใน Sport",
        "picture": "images/icon-3.png",
        "price": 79
    },
    {
        "id": "4",
        "name": "กางเกงในทรงกางเกง",
        "picture": "images/icon-4.png",
        "price": 79
    },
    {
        "id": "5",
        "name": "กางเกงใน เย็นจัด ลายพิเศษ",
        "picture": "images/icon-5.png",
        "price": 79
    },
    {
        "id": "6",
        "name": "กางเกงใน Sport ลายพิเศษ",
        "picture": "images/icon-6.png",
        "price": 79
    }
    
    
]